zeka/__init__.py
zeka/__main__.py
zeka-1.2.0.dist-info/METADATA
zeka-1.2.0.dist-info/WHEEL
zeka-1.2.0.dist-info/entry_points.txt
zeka-1.2.0.dist-info/RECORD
