Metadata-Version: 2.1
Name: zeka
Version: 1.2.0
Summary: 
License: MIT
Author: Niklas Alexander Shern
Author-email: nshern@protonmail.com
Requires-Python: >=3.12,<4.0
Classifier: License :: OSI Approved :: MIT License
Classifier: Programming Language :: Python :: 3
Classifier: Programming Language :: Python :: 3.12
Requires-Dist: python-frontmatter (>=1.0.0,<2.0.0)
Requires-Dist: pyyaml (>=6.0.1,<7.0.0)
Requires-Dist: randomname (>=0.2.1,<0.3.0)
